{
  "project_info": {
    "project_number": "738844052416",
    "firebase_url": "https://breakdownaid.firebaseio.com",
    "project_id": "breakdownaid",
    "storage_bucket": "breakdownaid.appspot.com"
  },
  "client": [
    {
      "client_info": {
        "mobilesdk_app_id": "1:738844052416:android:123a1b2bf94f945e",
        "android_client_info": {
          "package_name": "com.valentine.BreakdownAid"
        }
      },
      "oauth_client": [
        {
          "client_id": "738844052416-cn17u82r10r8u97lqtnhd4lqfogkdvng.apps.googleusercontent.com",
          "client_type": 1,
          "android_info": {
            "package_name": "com.valentine.BreakdownAid",
            "certificate_hash": "8a9eda871a9cf78a37c4d4dbdf047e6b7d350423"
          }
        },
        {
          "client_id": "738844052416-f757sbb687dvu59kvlorl4sbvi2o8ltr.apps.googleusercontent.com",
          "client_type": 3
        }
      ],
      "api_key": [
        {
          "current_key": "AIzaSyCct95CW_uorOmWnnx7MmMctlETUn0tt2o"
        }
      ],
      "services": {
        "analytics_service": {
          "status": 1
        },
        "appinvite_service": {
          "status": 2,
          "other_platform_oauth_client": [
            {
              "client_id": "738844052416-f757sbb687dvu59kvlorl4sbvi2o8ltr.apps.googleusercontent.com",
              "client_type": 3
            }
          ]
        },
        "ads_service": {
          "status": 2
        }
      }
    }
  ],
  "configuration_version": "1"
}